.gitignore
LICENSE
MANIFEST.in
README.rst
generate.py
setup.py
nnpy/__init__.py
nnpy/constants.py
nnpy/errors.py
nnpy/socket.py
nnpy/tests.py
nnpy.egg-info/PKG-INFO
nnpy.egg-info/SOURCES.txt
nnpy.egg-info/dependency_links.txt
nnpy.egg-info/requires.txt
nnpy.egg-info/top_level.txt