Metadata-Version: 1.1
Name: nnpy
Version: 1.4.2
Summary: cffi-based Python bindings for nanomsg
Home-page: https://github.com/nanomsg/nnpy
Author: Dirkjan Ochtman
Author-email: dirkjan@ochtman.nl
License: MIT
Platform: UNKNOWN
Classifier: Development Status :: 5 - Production/Stable
Classifier: Environment :: Web Environment
Classifier: Intended Audience :: Developers
Classifier: License :: OSI Approved :: MIT License
Classifier: Operating System :: OS Independent
Classifier: Programming Language :: Python
Classifier: Programming Language :: Python :: 2.7
Classifier: Programming Language :: Python :: 3
Classifier: Programming Language :: Python :: 3.3
Classifier: Programming Language :: Python :: 3.4
Classifier: Programming Language :: Python :: Implementation :: CPython
